cygsubprocess/LICENSE
cygsubprocess/README.MD
cygsubprocess/__init__.py
cygsubprocess/requirements.txt
cygsubprocess/thirdparty.json
cygsubprocess-0.12.dist-info/LICENSE.rst
cygsubprocess-0.12.dist-info/METADATA
cygsubprocess-0.12.dist-info/WHEEL
cygsubprocess-0.12.dist-info/top_level.txt
cygsubprocess-0.12.dist-info/RECORD
