Metadata-Version: 2.1
Name: cygsubprocess
Version: 0.12
Summary: Executes Cygwin bash scripts/commands in Python, captures and prints the output
Home-page: https://github.com/hansalemaos/cygsubprocess
Author: Johannes Fischer
Author-email: <aulasparticularesdealemaosp@gmail.com>
License: MIT
Keywords: bash,cygwin,sh,linux
Classifier: Development Status :: 4 - Beta
Classifier: Programming Language :: Python :: 3 :: Only
Classifier: Programming Language :: Python :: 3.10
Classifier: Topic :: Scientific/Engineering :: Visualization
Classifier: Topic :: Software Development :: Libraries :: Python Modules
Classifier: Topic :: Utilities
License-File: LICENSE.rst
Requires-Dist: add2winpath
Requires-Dist: requests
